ecowitt2aprs/__init__.py
ecowitt2aprs/__init__.py~
ecowitt2aprs/ecowitt2aprs.py
ecowitt2aprs-0.1.11.dist-info/WHEEL
ecowitt2aprs-0.1.11.dist-info/entry_points.txt
ecowitt2aprs-0.1.11.dist-info/METADATA
ecowitt2aprs-0.1.11.dist-info/RECORD
