Metadata-Version: 2.3
Name: ecowitt2aprs
Version: 0.1.11
Summary: Transform Ecowitt API JSON to APRS Complete Weather Report format
Keywords: APRS,Packet,Geolocation,Amateur Radio
Author: Chris Jewell
Author-email: Chris Jewell <chrism0dwk@gmail.com>
Classifier: Development Status :: 3 - Alpha
Classifier: Intended Audience :: Telecommunications Industry
Classifier: Intended Audience :: Science/Research
Classifier: Intended Audience :: Developers
Classifier: Topic :: Communications :: Ham Radio
Classifier: Programming Language :: Python :: 3
Classifier: Programming Language :: Python :: 3.11
Requires-Dist: argparse>=1.4.0
Requires-Dist: datetime>=5.5
Requires-Dist: pyyaml>=6.0.2
Requires-Dist: urllib3>=2.4.0
Maintainer: Chris Jewell
Maintainer-email: Chris Jewell <chrism0dwk@gmail.com>
Requires-Python: >=3.11
